[
  {
    "name": "Bansos",
    "stock": 0,
    "lastUpdate": "2025-12-29T00:50:19Z",
    "cycle": 1
  },
  {
    "name": "AKBAR RISQ",
    "stock": 26,
    "lastUpdate": "2025-12-29T00:31:11Z",
    "cycle": 5
  },
  {
    "name": "ALFIAN DWI A.",
    "stock": 40,
    "lastUpdate": "2025-12-29T00:31:11Z",
    "cycle": 5
  },
  {
    "name": "ATHI HANDAYANI",
    "stock": 0,
    "lastUpdate": "2025-12-29T00:31:11Z",
    "cycle": 1
  },
  {
    "name": "CINDRAWATI",
    "stock": 3,
    "lastUpdate": "2025-12-29T00:31:11Z",
    "cycle": 5
  },
  {
    "name": "EDI SUGENG SARIPAN",
    "stock": 0,
    "lastUpdate": "2025-12-29T01:14:28Z",
    "cycle": 1
  },
  {
    "name": "BINA MAKMUR",
    "stock": 31,
    "lastUpdate": "2025-12-29T00:31:33Z",
    "cycle": 5
  },
  {
    "name": "HENDRA KURNIAWAN",
    "stock": 23,
    "lastUpdate": "2025-12-29T00:35:32Z",
    "cycle": 5
  },
  {
    "name": "SUCIYONO",
    "stock": 15,
    "lastUpdate": "2025-12-29T00:35:35Z",
    "cycle": 5
  },
  {
    "name": "SUMBER REJEKI",
    "stock": 0,
    "lastUpdate": "2025-12-29T00:36:08Z",
    "cycle": 5
  },
  {
    "name": "JAENAL",
    "stock": 36,
    "lastUpdate": "2025-12-29T00:36:22Z",
    "cycle": 5
  },
  {
    "name": "JOKO SUWARNO",
    "stock": 9,
    "lastUpdate": "2025-12-29T00:41:48Z",
    "cycle": 5
  },
  {
    "name": "KARSONO",
    "stock": 38,
    "lastUpdate": "2025-12-29T01:14:28Z",
    "cycle": 5
  },
  {
    "name": "LUTFI A.",
    "stock": 42,
    "lastUpdate": "2025-12-29T01:14:28Z",
    "cycle": 5
  },
  {
    "name": "MOH SAID",
    "stock": 0,
    "lastUpdate": "2025-12-29T01:14:28Z",
    "cycle": 5
  },
  {
    "name": "TITIK ISMIATIN",
    "stock": 15,
    "lastUpdate": "2025-12-29T01:14:52Z",
    "cycle": 5
  },
  {
    "name": "TK. MAJU",
    "stock": 12,
    "lastUpdate": "2025-12-29T01:17:02Z",
    "cycle": 5
  },
  {
    "name": "TOKO 2 PUTRI",
    "stock": 0,
    "lastUpdate": "2025-12-29T01:17:46Z",
    "cycle": 5
  },
  {
    "name": "TOKO IIN",
    "stock": 27,
    "lastUpdate": "2025-12-29T01:18:09Z",
    "cycle": 5
  },
  {
    "name": "Bansos",
    "stock": 1,
    "lastUpdate": "2025-12-29T01:18:58Z",
    "cycle": 5
  },
  {
    "name": "Bansos",
    "stock": 1,
    "lastUpdate": "2025-12-29T01:29:18Z",
    "cycle": 5
  },
  {
    "name": "SUPARMAN",
    "stock": 0,
    "lastUpdate": "2025-12-29T01:24:56Z",
    "cycle": 1
  },
  {
    "name": "HJ LILIK LAILIYAH",
    "stock": 0,
    "lastUpdate": "2025-12-29T01:21:45Z",
    "cycle": 1
  },
  {
    "name": "ERNA PUJIATI",
    "stock": 0,
    "lastUpdate": "2025-12-29T01:24:56Z",
    "cycle": 1
  },
  {
    "name": "P. SUK",
    "stock": 0,
    "lastUpdate": "2025-12-29T01:39:30Z",
    "cycle": 3
  },
  {
    "name": "Bansos",
    "stock": 0,
    "lastUpdate": "2025-12-29T01:55:59Z",
    "cycle": 1
  },
  {
    "name": "JONI H",
    "stock": 0,
    "lastUpdate": "2025-12-28T22:57:43Z",
    "cycle": 0
  },
  {
    "name": "TOKO IRAWAN",
    "stock": 1,
    "lastUpdate": "2025-12-29T01:35:08Z",
    "cycle": 5
  },
  {
    "name": "YUNIS WAHYUNI",
    "stock": 0,
    "lastUpdate": "2025-12-29T01:21:45Z",
    "cycle": 1
  },
  {
    "name": "ROSA V",
    "stock": 0,
    "lastUpdate": "2025-12-29T01:21:47Z",
    "cycle": 1
  },
  {
    "name": "LUKMAN BS",
    "stock": 0,
    "lastUpdate": "2025-12-28T22:57:43Z",
    "cycle": 0
  },
  {
    "name": "BISTON MANURUNG",
    "stock": 0,
    "lastUpdate": "2025-12-29T01:22:06Z",
    "cycle": 1
  },
  {
    "name": "ROSIDI",
    "stock": 0,
    "lastUpdate": "2025-12-28T23:06:46Z",
    "cycle": 0
  },
  {
    "name": "JAMILAH",
    "stock": 0,
    "lastUpdate": "2025-12-28T23:10:46Z",
    "cycle": 0
  },
  {
    "name": "YUDA",
    "stock": 0,
    "lastUpdate": "2025-12-28T23:10:46Z",
    "cycle": 0
  },
  {
    "name": "SRI UTAMI",
    "stock": 0,
    "lastUpdate": "2025-12-29T01:24:59Z",
    "cycle": 2
  },
  {
    "name": "Bansos",
    "stock": 0,
    "lastUpdate": "2025-12-29T01:22:10Z",
    "cycle": 1
  },
  {
    "name": "BAMBANG HARTONO",
    "stock": 0,
    "lastUpdate": "2025-12-29T01:39:30Z",
    "cycle": 3
  },
  {
    "name": "HJ. ASLAMIYAH",
    "stock": 1,
    "lastUpdate": "2025-12-29T01:35:08Z",
    "cycle": 5
  },
  {
    "name": "NADIFATUS SOLEHA",
    "stock": 0,
    "lastUpdate": "2025-12-29T01:29:18Z",
    "cycle": 2
  },
  {
    "name": "ISTIQOMAH",
    "stock": 0,
    "lastUpdate": "2025-12-29T01:39:30Z",
    "cycle": 1
  },
  {
    "name": "SUROSO",
    "stock": 0,
    "lastUpdate": "2025-12-29T01:29:20Z",
    "cycle": 2
  },
  {
    "name": "HADI SUTOYO",
    "stock": 0,
    "lastUpdate": "2025-12-29T01:29:43Z",
    "cycle": 1
  },
  {
    "name": "SRI HIDAYATI",
    "stock": 0,
    "lastUpdate": "2025-12-29T01:39:30Z",
    "cycle": 2
  },
  {
    "name": "ONG SWI GIOK",
    "stock": 0,
    "lastUpdate": "2025-12-29T01:39:54Z",
    "cycle": 1
  },
  {
    "name": "YUSUF ISMAIL",
    "stock": 0,
    "lastUpdate": "2025-12-29T01:43:11Z",
    "cycle": 3
  },
  {
    "name": "SUPARNI",
    "stock": 0,
    "lastUpdate": "2025-12-29T01:43:11Z",
    "cycle": 3
  },
  {
    "name": "H. JUMAT",
    "stock": 0,
    "lastUpdate": "2025-12-29T01:43:11Z",
    "cycle": 3
  },
  {
    "name": "YOGA RAJAN",
    "stock": 0,
    "lastUpdate": "2025-12-29T01:43:11Z",
    "cycle": 2
  },
  {
    "name": "HARSININGSIH",
    "stock": 0,
    "lastUpdate": "2025-12-29T01:55:59Z",
    "cycle": 1
  },
  {
    "name": "ARIF FAUZI",
    "stock": 0,
    "lastUpdate": "2025-12-29T01:43:35Z",
    "cycle": 1
  },
  {
    "name": "Bansos",
    "stock": 41,
    "lastUpdate": "2025-12-29T01:49:22Z",
    "cycle": 5
  },
  {
    "name": "MOH HAFIF",
    "stock": 0,
    "lastUpdate": "2025-12-29T01:46:26Z",
    "cycle": 3
  },
  {
    "name": "CAHYA HERAWATI",
    "stock": 0,
    "lastUpdate": "2025-12-29T01:46:26Z",
    "cycle": 3
  },
  {
    "name": "Bansos",
    "stock": 0,
    "lastUpdate": "2025-12-29T01:43:38Z",
    "cycle": 1
  },
  {
    "name": "SAMSUL ARIFIN",
    "stock": 0,
    "lastUpdate": "2025-12-29T01:46:26Z",
    "cycle": 2
  },
  {
    "name": "WIKAN K",
    "stock": 0,
    "lastUpdate": "2025-12-29T01:46:29Z",
    "cycle": 2
  },
  {
    "name": "TUSOK",
    "stock": 0,
    "lastUpdate": "2025-12-29T01:46:48Z",
    "cycle": 1
  },
  {
    "name": "MISRI CICI",
    "stock": 0,
    "lastUpdate": "2025-12-29T01:49:22Z",
    "cycle": 3
  },
  {
    "name": "HERDIANA DIYAH S",
    "stock": 0,
    "lastUpdate": "2025-12-29T01:49:22Z",
    "cycle": 3
  },
  {
    "name": "BUDI",
    "stock": 0,
    "lastUpdate": "2025-12-29T01:49:22Z",
    "cycle": 3
  },
  {
    "name": "YULI SORAYA",
    "stock": 0,
    "lastUpdate": "2025-12-29T01:49:23Z",
    "cycle": 2
  },
  {
    "name": "SUSILO",
    "stock": 4,
    "lastUpdate": "2025-12-29T01:55:59Z",
    "cycle": 3
  },
  {
    "name": "HJ. HAERONI",
    "stock": 0,
    "lastUpdate": "2025-12-29T01:53:17Z",
    "cycle": 2
  },
  {
    "name": "IMA",
    "stock": 0,
    "lastUpdate": "2025-12-29T01:53:17Z",
    "cycle": 2
  },
  {
    "name": "DARMAWAN P",
    "stock": 0,
    "lastUpdate": "2025-12-29T01:53:17Z",
    "cycle": 2
  },
  {
    "name": "DIYAH UTAMI",
    "stock": 0,
    "lastUpdate": "2025-12-29T01:53:39Z",
    "cycle": 1
  },
  {
    "name": "SALMAH",
    "stock": 0,
    "lastUpdate": "2025-12-29T01:55:59Z",
    "cycle": 2
  },
  {
    "name": "TOKO ANITA",
    "stock": 0,
    "lastUpdate": "2025-12-29T01:56:01Z",
    "cycle": 2
  },
  {
    "name": "TK. LUCKY",
    "stock": 0,
    "lastUpdate": "2025-12-29T01:56:21Z",
    "cycle": 1
  },
  {
    "name": "UD SAMAN HADI",
    "stock": 1,
    "lastUpdate": "2025-12-29T01:56:24Z",
    "cycle": 1
  },
  {
    "name": "SOEKAMTO",
    "stock": 1,
    "lastUpdate": "2025-12-29T01:56:26Z",
    "cycle": 1
  },
  {
    "name": "TOKO TIARA",
    "stock": 0,
    "lastUpdate": "2025-12-28T22:53:24Z",
    "cycle": 0
  },
  {
    "name": "TOKO POJOK",
    "stock": 69,
    "lastUpdate": "2025-12-28T23:26:50Z",
    "cycle": 0
  },
  {
    "name": "UD RAHMAT",
    "stock": 41,
    "lastUpdate": "2025-12-28T23:02:02Z",
    "cycle": 0
  },
  {
    "name": "ULFA MARIA",
    "stock": 0,
    "lastUpdate": "2025-12-28T23:04:56Z",
    "cycle": 0
  },
  {
    "name": "TOKO SURYATI",
    "stock": 0,
    "lastUpdate": "2025-12-28T23:05:11Z",
    "cycle": 0
  },
  {
    "name": "SUDJIONO",
    "stock": 0,
    "lastUpdate": "2025-12-28T23:05:12Z",
    "cycle": 0
  },
  {
    "name": "ANDRI HERU CAHYONO",
    "stock": 0,
    "lastUpdate": "2025-12-28T23:16:09Z",
    "cycle": 0
  },
  {
    "name": "ABDUL WAFI",
    "stock": 69,
    "lastUpdate": "2025-12-28T23:40:51Z",
    "cycle": 0
  }
]