[
  {
    "name": "ABDUL WAFI",
    "stock": 0,
    "lastUpdate": "2025-10-31T05:30:10Z",
    "cycle": 0
  },
  {
    "name": "AKBAR RISQ",
    "stock": 0,
    "lastUpdate": "2025-10-31T05:30:10Z",
    "cycle": 0
  },
  {
    "name": "ALFIAN DWI A.",
    "stock": 102,
    "lastUpdate": "2025-10-31T07:53:40Z",
    "cycle": 5
  },
  {
    "name": "ATHI HANDAYANI",
    "stock": 24,
    "lastUpdate": "2025-10-31T07:53:40Z",
    "cycle": 5
  },
  {
    "name": "CINDRAWATI",
    "stock": 58,
    "lastUpdate": "2025-10-31T07:55:37Z",
    "cycle": 5
  },
  {
    "name": "EDI SUGENG SARIPAN",
    "stock": 40,
    "lastUpdate": "2025-10-31T07:55:39Z",
    "cycle": 5
  },
  {
    "name": "BINA MAKMUR",
    "stock": 158,
    "lastUpdate": "2025-10-31T08:02:05Z",
    "cycle": 2
  },
  {
    "name": "HENDRA KURNIAWAN",
    "stock": 146,
    "lastUpdate": "2025-10-31T08:02:05Z",
    "cycle": 2
  },
  {
    "name": "SUCIYONO",
    "stock": 174,
    "lastUpdate": "2025-10-31T08:03:43Z",
    "cycle": 2
  },
  {
    "name": "SUMBER REJEKI",
    "stock": 142,
    "lastUpdate": "2025-10-31T08:03:49Z",
    "cycle": 2
  },
  {
    "name": "JAENAL",
    "stock": 160,
    "lastUpdate": "2025-10-31T06:08:04Z",
    "cycle": 0
  },
  {
    "name": "JOKO SUWARNO",
    "stock": 126,
    "lastUpdate": "2025-10-31T06:25:57Z",
    "cycle": 0
  },
  {
    "name": "KARSONO",
    "stock": 127,
    "lastUpdate": "2025-10-31T06:27:38Z",
    "cycle": 0
  },
  {
    "name": "LUTFI A.",
    "stock": 187,
    "lastUpdate": "2025-10-31T07:07:55Z",
    "cycle": 0
  },
  {
    "name": "MOH SAID",
    "stock": 98,
    "lastUpdate": "2025-10-31T06:27:39Z",
    "cycle": 0
  },
  {
    "name": "TITIK ISMIATIN",
    "stock": 154,
    "lastUpdate": "2025-10-31T06:47:19Z",
    "cycle": 0
  },
  {
    "name": "TK. MAJU",
    "stock": 157,
    "lastUpdate": "2025-10-31T06:47:19Z",
    "cycle": 0
  },
  {
    "name": "TOKO 2 PUTRI",
    "stock": 6,
    "lastUpdate": "2025-10-31T07:33:13Z",
    "cycle": 0
  },
  {
    "name": "TOKO IIN",
    "stock": 81,
    "lastUpdate": "2025-10-31T06:49:19Z",
    "cycle": 0
  },
  {
    "name": "TOKO POJOK",
    "stock": 70,
    "lastUpdate": "2025-10-31T06:49:29Z",
    "cycle": 0
  },
  {
    "name": "UD RAHMAT",
    "stock": 2,
    "lastUpdate": "2025-10-31T07:07:55Z",
    "cycle": 0
  },
  {
    "name": "SUPARMAN",
    "stock": 14,
    "lastUpdate": "2025-10-31T07:09:30Z",
    "cycle": 0
  },
  {
    "name": "HJ LILIK LAILIYAH",
    "stock": 0,
    "lastUpdate": "2025-10-31T04:42:15Z",
    "cycle": 0
  },
  {
    "name": "ERNA PUJIATI",
    "stock": 0,
    "lastUpdate": "2025-10-31T04:43:18Z",
    "cycle": 0
  },
  {
    "name": "P. SUK",
    "stock": 0,
    "lastUpdate": "2025-10-31T04:43:18Z",
    "cycle": 0
  },
  {
    "name": "ANDRI HERU CAHYONO",
    "stock": 0,
    "lastUpdate": "2025-10-31T04:43:46Z",
    "cycle": 0
  },
  {
    "name": "JONI H",
    "stock": 0,
    "lastUpdate": "2025-10-31T04:43:48Z",
    "cycle": 0
  },
  {
    "name": "TOKO IRAWAN",
    "stock": 0,
    "lastUpdate": "2025-10-31T04:44:34Z",
    "cycle": 0
  },
  {
    "name": "YUNIS WAHYUNI",
    "stock": 0,
    "lastUpdate": "2025-10-31T04:44:34Z",
    "cycle": 0
  },
  {
    "name": "ROSA V",
    "stock": 0,
    "lastUpdate": "2025-10-31T04:44:57Z",
    "cycle": 0
  },
  {
    "name": "LUKMAN BS",
    "stock": 0,
    "lastUpdate": "2025-10-31T04:44:58Z",
    "cycle": 0
  },
  {
    "name": "BISTON MANURUNG",
    "stock": 0,
    "lastUpdate": "2025-10-31T04:45:51Z",
    "cycle": 0
  },
  {
    "name": "ROSIDI",
    "stock": 0,
    "lastUpdate": "2025-10-31T04:45:51Z",
    "cycle": 0
  },
  {
    "name": "JAMILAH",
    "stock": 0,
    "lastUpdate": "2025-10-31T04:46:55Z",
    "cycle": 0
  },
  {
    "name": "YUDA",
    "stock": 0,
    "lastUpdate": "2025-10-31T04:46:55Z",
    "cycle": 0
  },
  {
    "name": "SRI UTAMI",
    "stock": 0,
    "lastUpdate": "2025-10-31T04:48:19Z",
    "cycle": 0
  },
  {
    "name": "ULFA MARIA",
    "stock": 0,
    "lastUpdate": "2025-10-31T04:48:19Z",
    "cycle": 0
  },
  {
    "name": "BAMBANG HARTONO",
    "stock": 0,
    "lastUpdate": "2025-10-31T04:48:54Z",
    "cycle": 0
  },
  {
    "name": "HJ. ASLAMIYAH",
    "stock": 0,
    "lastUpdate": "2025-10-31T04:49:08Z",
    "cycle": 0
  },
  {
    "name": "NADIFATUS SOLEHA",
    "stock": 0,
    "lastUpdate": "2025-10-31T04:49:49Z",
    "cycle": 0
  },
  {
    "name": "ISTIQOMAH",
    "stock": 0,
    "lastUpdate": "2025-10-31T04:49:49Z",
    "cycle": 0
  },
  {
    "name": "SUROSO",
    "stock": 0,
    "lastUpdate": "2025-10-31T04:50:41Z",
    "cycle": 0
  },
  {
    "name": "HADI SUTOYO",
    "stock": 0,
    "lastUpdate": "2025-10-31T04:50:41Z",
    "cycle": 0
  },
  {
    "name": "SRI HIDAYATI",
    "stock": 35,
    "lastUpdate": "2025-10-31T07:09:56Z",
    "cycle": 0
  },
  {
    "name": "ONG SWI GIOK",
    "stock": 0,
    "lastUpdate": "2025-10-31T04:53:09Z",
    "cycle": 0
  },
  {
    "name": "YUSUF ISMAIL",
    "stock": 43,
    "lastUpdate": "2025-10-31T07:27:31Z",
    "cycle": 0
  },
  {
    "name": "SUPARNI",
    "stock": 0,
    "lastUpdate": "2025-10-31T04:55:00Z",
    "cycle": 0
  },
  {
    "name": "H. JUMAT",
    "stock": 0,
    "lastUpdate": "2025-10-31T07:28:41Z",
    "cycle": 0
  },
  {
    "name": "YOGA RAJAN",
    "stock": 0,
    "lastUpdate": "2025-10-31T05:13:20Z",
    "cycle": 0
  },
  {
    "name": "HARSININGSIH",
    "stock": 0,
    "lastUpdate": "2025-10-31T05:13:50Z",
    "cycle": 0
  },
  {
    "name": "ARIF FAUZI",
    "stock": 0,
    "lastUpdate": "2025-10-31T05:18:16Z",
    "cycle": 0
  },
  {
    "name": "TOKO SURYATI",
    "stock": 0,
    "lastUpdate": "2025-10-31T05:16:28Z",
    "cycle": 0
  },
  {
    "name": "MOH HAFIF",
    "stock": 0,
    "lastUpdate": "2025-10-31T05:15:33Z",
    "cycle": 0
  },
  {
    "name": "CAHYA HERAWATI",
    "stock": 0,
    "lastUpdate": "2025-10-31T05:15:44Z",
    "cycle": 0
  },
  {
    "name": "SUDJIONO",
    "stock": 0,
    "lastUpdate": "2025-10-31T05:18:16Z",
    "cycle": 0
  },
  {
    "name": "SAMSUL ARIFIN",
    "stock": 0,
    "lastUpdate": "2025-10-31T05:19:30Z",
    "cycle": 0
  },
  {
    "name": "WIKAN K",
    "stock": 0,
    "lastUpdate": "2025-10-31T05:19:30Z",
    "cycle": 0
  },
  {
    "name": "TUSOK",
    "stock": 0,
    "lastUpdate": "2025-10-31T05:19:58Z",
    "cycle": 0
  },
  {
    "name": "MISRI CICI",
    "stock": 0,
    "lastUpdate": "2025-10-31T05:20:03Z",
    "cycle": 0
  },
  {
    "name": "HERDIANA DIYAH S",
    "stock": 0,
    "lastUpdate": "2025-10-31T05:20:44Z",
    "cycle": 0
  },
  {
    "name": "BUDI",
    "stock": 0,
    "lastUpdate": "2025-10-31T05:20:44Z",
    "cycle": 0
  },
  {
    "name": "YULI SORAYA",
    "stock": 0,
    "lastUpdate": "2025-10-31T05:21:44Z",
    "cycle": 0
  },
  {
    "name": "SUSILO",
    "stock": 0,
    "lastUpdate": "2025-10-31T05:21:44Z",
    "cycle": 0
  },
  {
    "name": "HJ. HAERONI",
    "stock": 0,
    "lastUpdate": "2025-10-31T05:24:46Z",
    "cycle": 0
  },
  {
    "name": "IMA",
    "stock": 0,
    "lastUpdate": "2025-10-31T05:23:09Z",
    "cycle": 0
  },
  {
    "name": "DARMAWAN P",
    "stock": 0,
    "lastUpdate": "2025-10-31T05:23:38Z",
    "cycle": 0
  },
  {
    "name": "DIYAH UTAMI",
    "stock": 0,
    "lastUpdate": "2025-10-31T05:24:04Z",
    "cycle": 0
  },
  {
    "name": "SALMAH",
    "stock": 0,
    "lastUpdate": "2025-10-31T05:24:46Z",
    "cycle": 0
  },
  {
    "name": "TOKO ANITA",
    "stock": 0,
    "lastUpdate": "2025-10-31T05:27:20Z",
    "cycle": 0
  },
  {
    "name": "TK. LUCKY",
    "stock": 0,
    "lastUpdate": "2025-10-31T05:29:16Z",
    "cycle": 0
  },
  {
    "name": "UD SAMAN HADI",
    "stock": 0,
    "lastUpdate": "2025-10-31T05:27:47Z",
    "cycle": 0
  },
  {
    "name": "SOEKAMTO",
    "stock": 0,
    "lastUpdate": "2025-10-31T05:28:13Z",
    "cycle": 0
  },
  {
    "name": "TOKO TIARA",
    "stock": 0,
    "lastUpdate": "2025-10-31T05:29:16Z",
    "cycle": 0
  }
]