[
  {
    "name": "ABDUL WAFI",
    "stock": 30,
    "lastUpdate": "2025-11-03T22:19:21Z",
    "cycle": 5
  },
  {
    "name": "AKBAR RISQ",
    "stock": 25,
    "lastUpdate": "2025-11-03T22:31:17Z",
    "cycle": 5
  },
  {
    "name": "ALFIAN DWI A.",
    "stock": 29,
    "lastUpdate": "2025-11-03T23:38:15Z",
    "cycle": 5
  },
  {
    "name": "ATHI HANDAYANI",
    "stock": 0,
    "lastUpdate": "2025-11-03T23:38:15Z",
    "cycle": 4
  },
  {
    "name": "CINDRAWATI",
    "stock": 0,
    "lastUpdate": "2025-11-03T20:58:09Z",
    "cycle": 0
  },
  {
    "name": "EDI SUGENG SARIPAN",
    "stock": 0,
    "lastUpdate": "2025-11-03T23:48:59Z",
    "cycle": 4
  },
  {
    "name": "BINA MAKMUR",
    "stock": 25,
    "lastUpdate": "2025-11-03T22:31:17Z",
    "cycle": 5
  },
  {
    "name": "HENDRA KURNIAWAN",
    "stock": 0,
    "lastUpdate": "2025-11-03T22:19:21Z",
    "cycle": 5
  },
  {
    "name": "SUCIYONO",
    "stock": 17,
    "lastUpdate": "2025-11-03T23:24:06Z",
    "cycle": 5
  },
  {
    "name": "SUMBER REJEKI",
    "stock": 6,
    "lastUpdate": "2025-11-03T22:08:44Z",
    "cycle": 5
  },
  {
    "name": "JAENAL",
    "stock": 35,
    "lastUpdate": "2025-11-03T22:22:38Z",
    "cycle": 5
  },
  {
    "name": "JOKO SUWARNO",
    "stock": 1,
    "lastUpdate": "2025-11-03T22:23:40Z",
    "cycle": 5
  },
  {
    "name": "KARSONO",
    "stock": 1,
    "lastUpdate": "2025-11-03T23:24:06Z",
    "cycle": 5
  },
  {
    "name": "LUTFI A.",
    "stock": 31,
    "lastUpdate": "2025-11-03T22:52:48Z",
    "cycle": 5
  },
  {
    "name": "MOH SAID",
    "stock": 0,
    "lastUpdate": "2025-11-03T22:52:48Z",
    "cycle": 5
  },
  {
    "name": "TITIK ISMIATIN",
    "stock": 7,
    "lastUpdate": "2025-11-03T23:03:51Z",
    "cycle": 5
  },
  {
    "name": "TK. MAJU",
    "stock": 15,
    "lastUpdate": "2025-11-03T23:18:24Z",
    "cycle": 5
  },
  {
    "name": "TOKO 2 PUTRI",
    "stock": 0,
    "lastUpdate": "2025-11-03T23:08:44Z",
    "cycle": 4
  },
  {
    "name": "TOKO IIN",
    "stock": 12,
    "lastUpdate": "2025-11-03T23:18:49Z",
    "cycle": 5
  },
  {
    "name": "Bansos",
    "stock": 1,
    "lastUpdate": "2025-11-03T21:49:18Z",
    "cycle": 5
  },
  {
    "name": "UD RAHMAT",
    "stock": 0,
    "lastUpdate": "2025-11-03T22:39:57Z",
    "cycle": 1
  },
  {
    "name": "SUPARMAN",
    "stock": -1,
    "lastUpdate": "2025-11-03T22:50:35Z",
    "cycle": 1
  },
  {
    "name": "HJ LILIK LAILIYAH",
    "stock": -90,
    "lastUpdate": "2025-11-03T23:00:44Z",
    "cycle": 1
  },
  {
    "name": "ERNA PUJIATI",
    "stock": 0,
    "lastUpdate": "2025-11-03T23:09:25Z",
    "cycle": 1
  },
  {
    "name": "P. SUK",
    "stock": 0,
    "lastUpdate": "2025-11-03T23:09:51Z",
    "cycle": 1
  },
  {
    "name": "ANDRI HERU CAHYONO",
    "stock": -9,
    "lastUpdate": "2025-11-03T23:19:50Z",
    "cycle": 1
  },
  {
    "name": "JONI H",
    "stock": -32,
    "lastUpdate": "2025-11-03T23:20:01Z",
    "cycle": 1
  },
  {
    "name": "TOKO IRAWAN",
    "stock": 0,
    "lastUpdate": "2025-11-03T23:20:14Z",
    "cycle": 1
  },
  {
    "name": "YUNIS WAHYUNI",
    "stock": -30,
    "lastUpdate": "2025-11-03T23:28:15Z",
    "cycle": 1
  },
  {
    "name": "ROSA V",
    "stock": -3,
    "lastUpdate": "2025-11-03T23:28:42Z",
    "cycle": 1
  },
  {
    "name": "LUKMAN BS",
    "stock": 0,
    "lastUpdate": "2025-11-03T23:28:49Z",
    "cycle": 1
  },
  {
    "name": "BISTON MANURUNG",
    "stock": 0,
    "lastUpdate": "2025-11-03T23:29:09Z",
    "cycle": 1
  },
  {
    "name": "ROSIDI",
    "stock": 0,
    "lastUpdate": "2025-11-03T23:29:15Z",
    "cycle": 1
  },
  {
    "name": "JAMILAH",
    "stock": -7,
    "lastUpdate": "2025-11-03T23:32:38Z",
    "cycle": 1
  },
  {
    "name": "YUDA",
    "stock": -1,
    "lastUpdate": "2025-11-03T23:33:08Z",
    "cycle": 1
  },
  {
    "name": "SRI UTAMI",
    "stock": -19,
    "lastUpdate": "2025-11-03T23:38:15Z",
    "cycle": 2
  },
  {
    "name": "ULFA MARIA",
    "stock": -12,
    "lastUpdate": "2025-11-03T23:38:41Z",
    "cycle": 1
  },
  {
    "name": "BAMBANG HARTONO",
    "stock": -56,
    "lastUpdate": "2025-11-03T23:44:11Z",
    "cycle": 2
  },
  {
    "name": "HJ. ASLAMIYAH",
    "stock": -5,
    "lastUpdate": "2025-11-03T23:44:11Z",
    "cycle": 1
  },
  {
    "name": "NADIFATUS SOLEHA",
    "stock": -7,
    "lastUpdate": "2025-11-03T23:44:11Z",
    "cycle": 1
  },
  {
    "name": "ISTIQOMAH",
    "stock": 0,
    "lastUpdate": "2025-11-03T23:44:38Z",
    "cycle": 1
  },
  {
    "name": "SUROSO",
    "stock": 0,
    "lastUpdate": "2025-11-03T23:48:59Z",
    "cycle": 2
  },
  {
    "name": "HADI SUTOYO",
    "stock": 0,
    "lastUpdate": "2025-11-03T23:48:59Z",
    "cycle": 2
  },
  {
    "name": "SRI HIDAYATI",
    "stock": 0,
    "lastUpdate": "2025-11-03T23:48:59Z",
    "cycle": 1
  },
  {
    "name": "ONG SWI GIOK",
    "stock": 0,
    "lastUpdate": "2025-11-03T23:49:25Z",
    "cycle": 1
  },
  {
    "name": "YUSUF ISMAIL",
    "stock": 0,
    "lastUpdate": "2025-11-03T23:52:42Z",
    "cycle": 2
  },
  {
    "name": "SUPARNI",
    "stock": 0,
    "lastUpdate": "2025-11-03T23:52:42Z",
    "cycle": 2
  },
  {
    "name": "H. JUMAT",
    "stock": 0,
    "lastUpdate": "2025-11-03T23:52:42Z",
    "cycle": 1
  },
  {
    "name": "YOGA RAJAN",
    "stock": 0,
    "lastUpdate": "2025-11-03T23:52:42Z",
    "cycle": 1
  },
  {
    "name": "HARSININGSIH",
    "stock": -17,
    "lastUpdate": "2025-11-03T23:53:09Z",
    "cycle": 1
  },
  {
    "name": "ARIF FAUZI",
    "stock": 1,
    "lastUpdate": "2025-11-03T23:53:11Z",
    "cycle": 1
  },
  {
    "name": "TOKO SURYATI",
    "stock": 1,
    "lastUpdate": "2025-11-03T23:53:12Z",
    "cycle": 1
  },
  {
    "name": "MOH HAFIF",
    "stock": 0,
    "lastUpdate": "2025-11-03T20:24:10Z",
    "cycle": 0
  },
  {
    "name": "CAHYA HERAWATI",
    "stock": 0,
    "lastUpdate": "2025-11-03T20:24:10Z",
    "cycle": 0
  },
  {
    "name": "SUDJIONO",
    "stock": 0,
    "lastUpdate": "2025-11-03T20:24:37Z",
    "cycle": 0
  },
  {
    "name": "SAMSUL ARIFIN",
    "stock": 0,
    "lastUpdate": "2025-11-03T20:24:38Z",
    "cycle": 0
  },
  {
    "name": "WIKAN K",
    "stock": -50,
    "lastUpdate": "2025-11-03T20:27:25Z",
    "cycle": 0
  },
  {
    "name": "TUSOK",
    "stock": 0,
    "lastUpdate": "2025-11-03T20:27:25Z",
    "cycle": 0
  },
  {
    "name": "MISRI CICI",
    "stock": -32,
    "lastUpdate": "2025-11-03T20:27:25Z",
    "cycle": 0
  },
  {
    "name": "HERDIANA DIYAH S",
    "stock": 0,
    "lastUpdate": "2025-11-03T20:27:48Z",
    "cycle": 0
  },
  {
    "name": "BUDI",
    "stock": 0,
    "lastUpdate": "2025-11-03T20:27:50Z",
    "cycle": 0
  },
  {
    "name": "YULI SORAYA",
    "stock": 0,
    "lastUpdate": "2025-11-03T20:29:49Z",
    "cycle": 0
  },
  {
    "name": "SUSILO",
    "stock": 0,
    "lastUpdate": "2025-11-03T20:29:49Z",
    "cycle": 0
  },
  {
    "name": "HJ. HAERONI",
    "stock": 0,
    "lastUpdate": "2025-11-03T20:29:49Z",
    "cycle": 0
  },
  {
    "name": "IMA",
    "stock": 0,
    "lastUpdate": "2025-11-03T20:30:15Z",
    "cycle": 0
  },
  {
    "name": "DARMAWAN P",
    "stock": 0,
    "lastUpdate": "2025-11-03T20:30:16Z",
    "cycle": 0
  },
  {
    "name": "DIYAH UTAMI",
    "stock": 0,
    "lastUpdate": "2025-11-03T20:34:59Z",
    "cycle": 0
  },
  {
    "name": "SALMAH",
    "stock": 0,
    "lastUpdate": "2025-11-03T20:34:59Z",
    "cycle": 0
  },
  {
    "name": "TOKO ANITA",
    "stock": 0,
    "lastUpdate": "2025-11-03T20:34:59Z",
    "cycle": 0
  },
  {
    "name": "TK. LUCKY",
    "stock": 0,
    "lastUpdate": "2025-11-03T20:35:26Z",
    "cycle": 0
  },
  {
    "name": "UD SAMAN HADI",
    "stock": 0,
    "lastUpdate": "2025-11-03T20:35:28Z",
    "cycle": 0
  },
  {
    "name": "SOEKAMTO",
    "stock": 0,
    "lastUpdate": "2025-11-03T20:45:10Z",
    "cycle": 0
  },
  {
    "name": "TOKO TIARA",
    "stock": 0,
    "lastUpdate": "2025-11-03T20:37:26Z",
    "cycle": 0
  },
  {
    "name": "TOKO POJOK",
    "stock": 51,
    "lastUpdate": "2025-11-03T22:01:05Z",
    "cycle": 4
  }
]